imageryclient/__init__.py
imageryclient/composite.py
imageryclient/imagery.py
imageryclient/utils.py
imageryclient-1.0.3.dist-info/LICENSE
imageryclient-1.0.3.dist-info/METADATA
imageryclient-1.0.3.dist-info/WHEEL
imageryclient-1.0.3.dist-info/top_level.txt
imageryclient-1.0.3.dist-info/RECORD
