Metadata-Version: 2.1
Name: imageryclient
Version: 1.0.3
Summary: Front end tools for composite images for EM connectomics
Home-page: https://github.com/ceesem/ImageryClient
Author: Casey Schneider-Mizell
Author-email: caseysm@gmail.com
License-File: LICENSE
Requires-Dist: scipy
Requires-Dist: numpy
Requires-Dist: cloud-volume (>=8.0.0)
Requires-Dist: caveclient
Requires-Dist: Pillow
Requires-Dist: fastremap
Requires-Dist: tqdm
Requires-Dist: imageio
Requires-Dist: seaborn
